setup.py
cairy/__init__.py
cairy.egg-info/PKG-INFO
cairy.egg-info/SOURCES.txt
cairy.egg-info/dependency_links.txt
cairy.egg-info/top_level.txt