Metadata-Version: 1.1
Name: cairy
Version: 0.1
Summary: lightweight lib that allows easy transformation of data from one json mapping to another
Home-page: https://github.com/rutherford/cairy
Author: Matt Rutherford
Author-email: rutherford@clientsideweb.net
License: MIT
Keywords: json template mapping transformation
Platform: UNKNOWN
Classifier: Development Status :: 3 - Alpha
Classifier: Intended Audience :: Developers
Classifier: Topic :: Software Development :: Libraries :: Python Modules
Classifier: License :: OSI Approved :: MIT License
Classifier: Programming Language :: Python :: 2.7
